stellate_strawberry/__init__.py
stellate_strawberry-1.1.1.dist-info/METADATA
stellate_strawberry-1.1.1.dist-info/WHEEL
stellate_strawberry-1.1.1.dist-info/RECORD
