Metadata-Version: 2.1
Name: stellate-strawberry
Version: 1.1.1
Summary: Integrate Stellate with your Strawberry GraphQL API
Author: Stellate
Author-email: eng@stellate.co
Requires-Python: >=3.9,<4.0
Classifier: Programming Language :: Python :: 3
Classifier: Programming Language :: Python :: 3.9
Classifier: Programming Language :: Python :: 3.10
Classifier: Programming Language :: Python :: 3.11
Classifier: Programming Language :: Python :: 3.12
Requires-Dist: requests (>=2.31.0,<3.0.0)
